MANIFEST.in
README.md
requirements.txt
setup.cfg
setup.py
KI_Hosting.egg-info/PKG-INFO
KI_Hosting.egg-info/SOURCES.txt
KI_Hosting.egg-info/dependency_links.txt
KI_Hosting.egg-info/not-zip-safe
KI_Hosting.egg-info/requires.txt
KI_Hosting.egg-info/top_level.txt
bin/fi:generate
bin/fi:remove
bin/req:handle
examples/monclub.py
ki_hosting/__init__.py
ki_hosting/handle.py
ki_hosting/models.py
ki_hosting/version.py
ki_hosting/templates/fiche.tex
ki_hosting/templates/row.tex
ki_hosting/templates/table.tex