Metadata-Version: 1.0
Name: KI-Hosting
Version: 1.0.1
Summary: Manage hosting at KI Ecole Des Ponts
Home-page: http://github.com/KIClubinfo/ki-hosting
Author: Philippe Ferreira De Sousa
Author-email: philippe@fdesousa.fr
License: MIT
Keywords: generate ki clubinfo fiche club asso
Platform: UNKNOWN
